LICENSE.md
MANIFEST.in
README.md
requirements.txt
setup.py
bin/run_sharpener
bin/run_sharpener_mp
bin/sharpipeline
sharpener/__init__.py
sharpener/sharpener.py
sharpener/sharpener_default.yml
sharpener.egg-info/PKG-INFO
sharpener.egg-info/SOURCES.txt
sharpener.egg-info/dependency_links.txt
sharpener.egg-info/requires.txt
sharpener.egg-info/top_level.txt
sharpener/sharp_modules/__init__.py
sharpener/sharp_modules/absorption_plot.py
sharpener/sharp_modules/abstack.py
sharpener/sharp_modules/cont_src.py
sharpener/sharp_modules/convert_units.py
sharpener/sharp_modules/cubez.py
sharpener/sharp_modules/hi.py
sharpener/sharp_modules/kk.py
sharpener/sharp_modules/mirlib.py
sharpener/sharp_modules/sdss_match.py
sharpener/sharp_modules/spec_ex.py
tutorials/T1_spectra_extraction.ipynb
tutorials/T2_automated_run.ipynb
tutorials/T3_continuum_image_tools.ipynb
tutorials/T4_stacking_spectra.ipynb