Metadata-Version: 2.1
Name: sharpener
Version: 1.0.8
Summary: sharpener is a tool to identify the position of all continuum sources in a continuum image and extract a spectrum from each line of sight of these sources.
Home-page: https://github.com/Fil8/SHARPener
Author: Filippo Marcello Maccagni
Author-email: filippo.maccagni@gmail.com
License: GNU GPL 3
Platform: OS Independent
Classifier: Intended Audience :: Developers
Classifier: Programming Language :: Python :: 2
Classifier: Topic :: Scientific/Engineering :: Astronomy
Classifier: Topic :: Software Development :: Libraries :: Python Modules
